mkdocs_get_deps/__init__.py
mkdocs_get_deps/__main__.py
mkdocs_get_deps/cache.py
mkdocs_get_deps/py.typed
mkdocs_get_deps/yaml_util.py
mkdocs_get_deps-0.1.0.dist-info/METADATA
mkdocs_get_deps-0.1.0.dist-info/WHEEL
mkdocs_get_deps-0.1.0.dist-info/entry_points.txt
mkdocs_get_deps-0.1.0.dist-info/licenses/LICENSE.md
mkdocs_get_deps-0.1.0.dist-info/RECORD
