Metadata-Version: 2.1
Name: mkdocs-get-deps
Version: 0.1.0
Summary: MkDocs extension that lists all dependencies according to a mkdocs.yml file
Project-URL: Source, https://github.com/mkdocs/get-deps
Project-URL: Issues, https://github.com/mkdocs/get-deps/issues
Project-URL: History, https://github.com/mkdocs/get-deps/releases
Author-email: Oleh Prypin <oleh@pryp.in>
License-Expression: MIT
License-File: LICENSE.md
Keywords: mkdocs
Classifier: Development Status :: 4 - Beta
Classifier: Environment :: Console
Classifier: Environment :: Web Environment
Classifier: Intended Audience :: Information Technology
Classifier: License :: OSI Approved :: MIT License
Classifier: Operating System :: OS Independent
Classifier: Programming Language :: Python
Classifier: Programming Language :: Python :: 3.8
Classifier: Programming Language :: Python :: 3.9
Classifier: Programming Language :: Python :: 3.10
Classifier: Programming Language :: Python :: 3.11
Classifier: Programming Language :: Python :: 3.12
Classifier: Topic :: Software Development :: Documentation
Classifier: Typing :: Typed
Requires-Python: >=3.8
Requires-Dist: importlib-metadata>=4.3; python_version < '3.10'
Requires-Dist: mergedeep>=1.3.4
Requires-Dist: platformdirs>=2.2.0
Requires-Dist: pyyaml>=5.1
